bits/__init__.py
bits/auth/__init__.py
bits_auth-3.0.1.dist-info/METADATA
bits_auth-3.0.1.dist-info/WHEEL
bits_auth-3.0.1.dist-info/RECORD
